SCA11H/__init__.py
SCA11H/commands/__init__.py
SCA11H/commands/base/Command.py
SCA11H/commands/base/GetCommand.py
SCA11H/commands/base/PostCommand.py
SCA11H/commands/base/__init__.py
SCA11H/commands/bcg/CalibrationPhase.py
SCA11H/commands/bcg/CalibrationStatus.py
SCA11H/commands/bcg/CallibrationStep.py
SCA11H/commands/bcg/Direction.py
SCA11H/commands/bcg/GetBasicInfo.py
SCA11H/commands/bcg/GetCalibrationStatus.py
SCA11H/commands/bcg/GetDirection.py
SCA11H/commands/bcg/GetFirmwareInfo.py
SCA11H/commands/bcg/GetParams.py
SCA11H/commands/bcg/GetRunningMode.py
SCA11H/commands/bcg/GetSerial.py
SCA11H/commands/bcg/Mode.py
SCA11H/commands/bcg/Parameters.py
SCA11H/commands/bcg/RunCommand.py
SCA11H/commands/bcg/SetDirection.py
SCA11H/commands/bcg/SetParams.py
SCA11H/commands/bcg/SetRunningMode.py
SCA11H/commands/bcg/StartCalibration.py
SCA11H/commands/bcg/UpgradeFirmware.py
SCA11H/commands/bcg/__init__.py
SCA11H/commands/system/CommunicationSettings.py
SCA11H/commands/system/GetActiveNetworkInfo.py
SCA11H/commands/system/GetBasicInfo.py
SCA11H/commands/system/GetCommunicationSettings.py
SCA11H/commands/system/GetFirmwareInfo.py
SCA11H/commands/system/GetHTTPUsername.py
SCA11H/commands/system/GetMAC.py
SCA11H/commands/system/GetNetworkSettings.py
SCA11H/commands/system/GetOTASettings.py
SCA11H/commands/system/GetSignalStrength.py
SCA11H/commands/system/GetWebpageLanguage.py
SCA11H/commands/system/GetWiFiCountryCode.py
SCA11H/commands/system/NetworkSecurityType.py
SCA11H/commands/system/OTASettings.py
SCA11H/commands/system/RunCommand.py
SCA11H/commands/system/ScanNetworks.py
SCA11H/commands/system/SetAlias.py
SCA11H/commands/system/SetCommunicationSettings.py
SCA11H/commands/system/SetHTTPPassword.py
SCA11H/commands/system/SetNetworkSettings.py
SCA11H/commands/system/SetOTASettings.py
SCA11H/commands/system/SetWebpageLanguage.py
SCA11H/commands/system/SetWiFiCountryCode.py
SCA11H/commands/system/UpgradeFirmware.py
SCA11H/commands/system/WebpageLanguage.py
SCA11H-0.1.0.dist-info/LICENSE
SCA11H-0.1.0.dist-info/METADATA
SCA11H-0.1.0.dist-info/WHEEL
SCA11H-0.1.0.dist-info/top_level.txt
SCA11H-0.1.0.dist-info/RECORD
