Metadata-Version: 2.1
Name: SCA11H
Version: 0.1.0
Summary: SCA11H Bed Sensor API Helper
Home-page: https://github.com/ihutano/SCA11H
Author: Dennis Sitelew
Author-email: yowidin@gmail.com
License: MIT
Project-URL: Bug Tracker, https://github.com/ihutano/SCA11H/issues
Platform: UNKNOWN
Classifier: Programming Language :: Python :: 3
Classifier: License :: OSI Approved :: MIT License
Classifier: Operating System :: OS Independent
Requires-Python: >=3.6
License-File: LICENSE
